CHANGES.rst
MANIFEST.in
README.rst
flake8_i18n.py
run_tests.py
setup.cfg
setup.py
flake8_i18n.egg-info/PKG-INFO
flake8_i18n.egg-info/SOURCES.txt
flake8_i18n.egg-info/dependency_links.txt
flake8_i18n.egg-info/entry_points.txt
flake8_i18n.egg-info/not-zip-safe
flake8_i18n.egg-info/requires.txt
flake8_i18n.egg-info/top_level.txt