Metadata-Version: 1.1
Name: flake8-i18n
Version: 0.1.0
Summary: Warns about incorrect gettext usage.
Home-page: https://github.com/vharitonsky/flake8-i18n
Author: Vitaliy Kharitonskiy
Author-email: gil.gnome@gmail.com
License: Free
Keywords: pep8 flake8 i18n
Platform: UNKNOWN
Classifier: Development Status :: 5 - Production/Stable
Classifier: Environment :: Console
Classifier: Intended Audience :: Developers
Classifier: License :: OSI Approved :: GNU General Public License v2 (GPLv2)
Classifier: Operating System :: OS Independent
Classifier: Programming Language :: Python
Classifier: Programming Language :: Python :: 3.6
Classifier: Programming Language :: Python :: 3.7
Classifier: Topic :: Software Development :: Quality Assurance
